{
  "id": "1770961172877",
  "timestamp": "2026-02-13T05:39:32.877Z",
  "market": "BNBUSDT",
  "signals": [
    {
      "strategy": "spot_stochastic_005",
      "timeframe": "timeframe5m",
      "strength": 91
    }
  ],
  "positionValue": 5,
  "status": "executed",
  "executionDetails": {
    "orderId": "PAPER-1770961172876",
    "quantity": 0.008298066550493735,
    "price": 602.55,
    "finalValueUSD": 5
  },
  "stopWinLoss": {
    "takeProfitPercentage": 4,
    "stopLossPercentage": 2,
    "takeProfitPrice": 626.6519999999999,
    "stopLossPrice": 590.4989999999999
  }
}