{
  "timestamp": "2026-02-16T01:48:25.377Z",
  "cycle": 20278,
  "roi24h": 0,
  "roi12h": 0,
  "roi6h": 0,
  "winRate": 42.06526785714286,
  "botsAlive": 25,
  "totalBots": 25,
  "groups": [
    {
      "groupId": "ALPHA",
      "bankroll": 501.64,
      "roi": 0.32799999999999724,
      "generation": 120,
      "winRate": 28.28,
      "totalTrades": 359,
      "activeStrategies": 81
    },
    {
      "groupId": "BETA",
      "bankroll": 514.17,
      "roi": 2.8339999999999916,
      "generation": 55,
      "winRate": 39.26,
      "totalTrades": 462,
      "activeStrategies": 87
    },
    {
      "groupId": "GAMMA",
      "bankroll": 507.16,
      "roi": 1.432000000000005,
      "generation": 26,
      "winRate": 23.18,
      "totalTrades": 92,
      "activeStrategies": 72
    },
    {
      "groupId": "DELTA",
      "bankroll": 499.16,
      "roi": -0.167999999999995,
      "generation": 83,
      "winRate": 34.220000000000006,
      "totalTrades": 122,
      "activeStrategies": 81
    },
    {
      "groupId": "OMEGA",
      "bankroll": 506.66,
      "roi": 1.332000000000005,
      "generation": 56,
      "winRate": 34.5,
      "totalTrades": 85,
      "activeStrategies": 80
    }
  ],
  "mutations": [],
  "cyclesCompleted": 0,
  "performance": {
    "peakBankroll": 2593.53,
    "peakToCurrentRetraction": null,
    "tradesTotal": 1120,
    "tradesWon": 471,
    "tradesLost": 649,
    "avgTradeSize": null,
    "bestTrade": 113.55,
    "worstTrade": 98.77
  }
}