{
  "timestamp": "2026-02-19T13:16:48.047Z",
  "cycle": 47913,
  "roi24h": 0,
  "roi12h": 0,
  "roi6h": 0,
  "winRate": 48.16808883693747,
  "botsAlive": 25,
  "totalBots": 25,
  "groups": [
    {
      "groupId": "ALPHA",
      "bankroll": 500.11,
      "roi": 0.02200000000000273,
      "generation": 1,
      "winRate": 32.260000000000005,
      "totalTrades": 1000,
      "activeStrategies": 114
    },
    {
      "groupId": "BETA",
      "bankroll": 500.74,
      "roi": 0.14800000000000182,
      "generation": 1,
      "winRate": 27.619999999999997,
      "totalTrades": 52,
      "activeStrategies": 96
    },
    {
      "groupId": "GAMMA",
      "bankroll": 501.92,
      "roi": 0.38400000000000317,
      "generation": 1,
      "winRate": 33.98,
      "totalTrades": 346,
      "activeStrategies": 101
    },
    {
      "groupId": "DELTA",
      "bankroll": 500.01,
      "roi": 0.001999999999998181,
      "generation": 1,
      "winRate": 30,
      "totalTrades": 13,
      "activeStrategies": 115
    },
    {
      "groupId": "OMEGA",
      "bankroll": 500.59,
      "roi": 0.117999999999995,
      "generation": 1,
      "winRate": 53.339999999999996,
      "totalTrades": 300,
      "activeStrategies": 111
    }
  ],
  "mutations": [],
  "cyclesCompleted": 0,
  "performance": {
    "peakBankroll": 2593.53,
    "peakToCurrentRetraction": null,
    "tradesTotal": 1711,
    "tradesWon": 824,
    "tradesLost": 887,
    "avgTradeSize": null,
    "bestTrade": 101.23,
    "worstTrade": 99.96
  }
}